Workbook

Sheet Summary
A1: UDP Migration Report - SAP PowerDesigner to erwin Data Modeler
A3: Run Information
A4: Report generated | B4: 2026-09-05 20:21:02
A5: Model name | B5: 03_Lubes_Sales_Marketing_Indirect_Channel_Portfolio_LDM_updated
A6: Source SAP model | B6: C:\Users\Shivansh\Downloads\migration-platform_4_sept_final\sappdmodels\ldm\03_Lubes_Sales_Marketing_Indirect_Channel_Portfolio_LDM_updated.ldm | C6: PowerDesigner model read for this run.
A7: Target erwin model | B7: n/a | C7: File the UDPs were written into.
A8: PowerDesigner version | B8: 16.7.0.6372
A9: Repository extraction id | B9: 30512774 | C9: Proves which point-in-time extract this migration came from.
A10: Injection executed | B10: No - report built from source data only | C10: Values below are reported as Not Verified because no injection result file was available.
A11: erwin session | B11: Not recorded
A13: Source Model (SAP PowerDesigner)
A14: Complexity band | B14: B4 - High / Very High | C14: From sow_classify.py, per the SOW Complexity Classification Spectrum.
A15: SOW automation range | B15: 20% to 50%
A16: Entities in source model | B16: 30
A17: Attributes in source model | B17: 182
A18: Extension properties found | B18: 0
A19: Extension values found | B19: 0
A21: UDP Definitions
A22: UDP definitions requested | B22: =MAX(0,COUNTA('UDP Definition'!$A:$A)-1) | C22: Each UDP is defined twice in erwin, once for the Entity owner and once for the Model owner.
A23: Created in erwin dictionary | B23: =COUNTIF('UDP Definition'!$J:$J,"Created*") | C23: Counted per UDP, not per owner.
A24: Updated in erwin dictionary | B24: =COUNTIF('UDP Definition'!$J:$J,"Updated*") | C24: UDPs that already existed in the target model and were re-pointed.
A25: Definition failures | B25: =COUNTIF('UDP Definition'!$N:$N,"FAILED*") | C25: A UDP counts as failed if erwin rejected either owner definition. See the Exceptions sheet for the reason.
A27: Value Reconciliation
A28: Entities matched in erwin | B28: Not recorded | C28: Entities the injector found in the target .erwin model.
A29: Source values to migrate | B29: =MAX(0,COUNTA('Value Reconciliation'!$C:$C)-1)
A30: Applied to erwin | B30: =COUNTIF('Value Reconciliation'!$H:$H,"Applied*")
A31: Applied and verified (read back) | B31: =COUNTIF('Value Reconciliation'!$I:$I,"Match") | C31: Value was written, then read back out of erwin and compared.
A32: Applied but value altered | B32: =COUNTIF('Value Reconciliation'!$I:$I,"Mismatch")
A33: Not applied | B33: =COUNTIF('Value Reconciliation'!$H:$H,"Skipped*")
A34: Blank source values | B34: =COUNTBLANK('Value Reconciliation'!$E$2:$E$91) | C34: Properties present in PowerDesigner but holding no value.
A36: Result
A37: Application rate | B37: =IF(B29=0,0,B30/B29) | C37: Share of source values erwin accepted.
A38: Verification rate | B38: =IF(B29=0,0,B31/B29) | C38: Share of source values confirmed identical inside erwin.
A39: High severity exceptions | B39: =COUNTIF(Exceptions!$A:$A,"High") | C39: Listed on the Exceptions sheet.
A40: Migration verdict | B40: NOT VERIFIED - NO INJECTION RESULTS | C40: This report was built from source data alone. Re-run batch_run.py to produce a verified report.
A42: Counts on this sheet are live formulas over the other three sheets, so they stay correct if rows are filtered or corrected during review.

Sheet UDP Definition
A1: UDP Name | B1: Inferred Type | C1: Length | D1: Value List (Observed) | E1: Source Path | F1: Source Coverage | G1: Distinct Observed | H1: List Source | I1: erwin Owner Types | J1: erwin Dictionary Action | K1: Values Expected | L1: Values Applied | M1: Values Verified | N1: Definition Status
A2: PD_ObjectID | B2: Text | C2: 40 | I2: Entity, Model | J2: Not Recorded | K2: =COUNTIF('Value Reconciliation'!$C:$C,$A2) | L2: =COUNTIFS('Value Reconciliation'!$C:$C,$A2,'Value Reconciliation'!$H:$H,"Applied*") | M2: =COUNTIFS('Value Reconciliation'!$C:$C,$A2,'Value Reconciliation'!$I:$I,"Match") | N2: Defined
A3: PD_SourceExtraction | B3: Text | C3: 20 | I3: Entity, Model | J3: Not Recorded | K3: =COUNTIF('Value Reconciliation'!$C:$C,$A3) | L3: =COUNTIFS('Value Reconciliation'!$C:$C,$A3,'Value Reconciliation'!$H:$H,"Applied*") | M3: =COUNTIFS('Value Reconciliation'!$C:$C,$A3,'Value Reconciliation'!$I:$I,"Match") | N3: Defined
A4: PD_SourceModel | B4: Text | C4: 120 | I4: Entity, Model | J4: Not Recorded | K4: =COUNTIF('Value Reconciliation'!$C:$C,$A4) | L4: =COUNTIFS('Value Reconciliation'!$C:$C,$A4,'Value Reconciliation'!$H:$H,"Applied*") | M4: =COUNTIFS('Value Reconciliation'!$C:$C,$A4,'Value Reconciliation'!$I:$I,"Match") | N4: Defined

Sheet Value Reconciliation
A1: Entity Name | B1: PD Object ID | C1: UDP | D1: Source Path | E1: Source Value (PowerDesigner) | F1: Target Value (erwin) | G1: Applied To | H1: Status | I1: Match | J1: Notes
A2: INVOICE | B2: 84EA5DD8-6A1A-45B8-8B2D-56057B619E63 | C2: PD_ObjectID | E2: 84EA5DD8-6A1A-45B8-8B2D-56057B619E63 | G2: Entity | H2: Not Verified - No Injection Result | I2: Not Applied | J2: No injection result recorded for this value.
A3: INVOICE | B3: 84EA5DD8-6A1A-45B8-8B2D-56057B619E63 | C3: PD_SourceExtraction | E3: 46603045 | G3: Entity | H3: Not Verified - No Injection Result | I3: Not Applied | J3: No injection result recorded for this value.
A4: INVOICE | B4: 84EA5DD8-6A1A-45B8-8B2D-56057B619E63 | C4: PD_SourceModel | E4: 03_Lubes_Sales_Marketing_Indirect_Channel_Portfolio_LDM_updated | G4: Entity | H4: Not Verified - No Injection Result | I4: Not Applied | J4: No injection result recorded for this value.
A5: DISCOUNT | B5: FD78AA7B-4711-4963-8DB9-ECB1B24D0E68 | C5: PD_ObjectID | E5: FD78AA7B-4711-4963-8DB9-ECB1B24D0E68 | G5: Entity | H5: Not Verified - No Injection Result | I5: Not Applied | J5: No injection result recorded for this value.
A6: DISCOUNT | B6: FD78AA7B-4711-4963-8DB9-ECB1B24D0E68 | C6: PD_SourceExtraction | E6: 46603045 | G6: Entity | H6: Not Verified - No Injection Result | I6: Not Applied | J6: No injection result recorded for this value.
A7: DISCOUNT | B7: FD78AA7B-4711-4963-8DB9-ECB1B24D0E68 | C7: PD_SourceModel | E7: 03_Lubes_Sales_Marketing_Indirect_Channel_Portfolio_LDM_updated | G7: Entity | H7: Not Verified - No Injection Result | I7: Not Applied | J7: No injection result recorded for this value.
A8: ACCOUNTS_RECEIVABLE | B8: 74B87F8A-E51D-4E06-AA56-48EA81D65346 | C8: PD_ObjectID | E8: 74B87F8A-E51D-4E06-AA56-48EA81D65346 | G8: Entity | H8: Not Verified - No Injection Result | I8: Not Applied | J8: No injection result recorded for this value.
A9: ACCOUNTS_RECEIVABLE | B9: 74B87F8A-E51D-4E06-AA56-48EA81D65346 | C9: PD_SourceExtraction | E9: 46603045 | G9: Entity | H9: Not Verified - No Injection Result | I9: Not Applied | J9: No injection result recorded for this value.
A10: ACCOUNTS_RECEIVABLE | B10: 74B87F8A-E51D-4E06-AA56-48EA81D65346 | C10: PD_SourceModel | E10: 03_Lubes_Sales_Marketing_Indirect_Channel_Portfolio_LDM_updated | G10: Entity | H10: Not Verified - No Injection Result | I10: Not Applied | J10: No injection result recorded for this value.
A11: DISTRIBUTOR_ANNUAL_TARGET | B11: 73C53A15-DAA2-4BDF-ACB0-E72E49B7EA1C | C11: PD_ObjectID | E11: 73C53A15-DAA2-4BDF-ACB0-E72E49B7EA1C | G11: Entity | H11: Not Verified - No Injection Result | I11: Not Applied | J11: No injection result recorded for this value.
A12: DISTRIBUTOR_ANNUAL_TARGET | B12: 73C53A15-DAA2-4BDF-ACB0-E72E49B7EA1C | C12: PD_SourceExtraction | E12: 46603045 | G12: Entity | H12: Not Verified - No Injection Result | I12: Not Applied | J12: No injection result recorded for this value.
A13: DISTRIBUTOR_ANNUAL_TARGET | B13: 73C53A15-DAA2-4BDF-ACB0-E72E49B7EA1C | C13: PD_SourceModel | E13: 03_Lubes_Sales_Marketing_Indirect_Channel_Portfolio_LDM_updated | G13: Entity | H13: Not Verified - No Injection Result | I13: Not Applied | J13: No injection result recorded for this value.
... A91: PRODUCT_FAMILY | B91: 300EC709-67F2-4014-A2D8-5F43A0F9C5D8 | C91: PD_SourceModel | E91: 03_Lubes_Sales_Marketing_Indirect_Channel_Portfolio_LDM_updated | G91: Entity | H91: Not Verified - No Injection Result | I91: Not Applied | J91: No injection result recorded for this value.

Sheet Exceptions
A1: Severity | B1: Category | C1: Entity | D1: UDP | E1: Detail | F1: Recommended Action
A2: Medium | B2: Not verified | C2: ACCOUNTS_RECEIVABLE | D2: PD_ObjectID | E2: No injection result was recorded for this value. | F2: Re-run batch_run.py so the report is built from a live injection result.
A3: Medium | B3: Not verified | C3: ACCOUNTS_RECEIVABLE | D3: PD_SourceExtraction | E3: No injection result was recorded for this value. | F3: Re-run batch_run.py so the report is built from a live injection result.
A4: Medium | B4: Not verified | C4: ACCOUNTS_RECEIVABLE | D4: PD_SourceModel | E4: No injection result was recorded for this value. | F4: Re-run batch_run.py so the report is built from a live injection result.
A5: Medium | B5: Not verified | C5: CAMPAIGN_SOURCE | D5: PD_ObjectID | E5: No injection result was recorded for this value. | F5: Re-run batch_run.py so the report is built from a live injection result.
A6: Medium | B6: Not verified | C6: CAMPAIGN_SOURCE | D6: PD_SourceExtraction | E6: No injection result was recorded for this value. | F6: Re-run batch_run.py so the report is built from a live injection result.
A7: Medium | B7: Not verified | C7: CAMPAIGN_SOURCE | D7: PD_SourceModel | E7: No injection result was recorded for this value. | F7: Re-run batch_run.py so the report is built from a live injection result.
A8: Medium | B8: Not verified | C8: COUNTRY | D8: PD_ObjectID | E8: No injection result was recorded for this value. | F8: Re-run batch_run.py so the report is built from a live injection result.
A9: Medium | B9: Not verified | C9: COUNTRY | D9: PD_SourceExtraction | E9: No injection result was recorded for this value. | F9: Re-run batch_run.py so the report is built from a live injection result.
A10: Medium | B10: Not verified | C10: COUNTRY | D10: PD_SourceModel | E10: No injection result was recorded for this value. | F10: Re-run batch_run.py so the report is built from a live injection result.
A11: Medium | B11: Not verified | C11: CUSTOMER | D11: PD_ObjectID | E11: No injection result was recorded for this value. | F11: Re-run batch_run.py so the report is built from a live injection result.
A12: Medium | B12: Not verified | C12: CUSTOMER | D12: PD_SourceExtraction | E12: No injection result was recorded for this value. | F12: Re-run batch_run.py so the report is built from a live injection result.
... A91: Medium | B91: Not verified | C91: SURVEY | D91: PD_SourceModel | E91: No injection result was recorded for this value. | F91: Re-run batch_run.py so the report is built from a live injection result.
A92: Informational | B92: Not carried by the erwin bridge | D92: Glossary term bindings (UseTerm) | E92: 86 term shortcuts - NOT delivered - external .glm has no erwin equivalent | F92: NOT RECOVERABLE as-is. SOW covers under 'naming standards, macros, templates - not automatically migrated'. Re-establish in erwin Naming Standards or relocate to Collibra.
A93: Informational | B93: Not carried by the erwin bridge | D93: GTL templates (relationship assertion, FK naming) | E93: 2 - NOT delivered | F93: NOT RECOVERABLE. SOW covers under 'model macros - manual rewrite required'.
A94: Informational | B94: Not carried by the erwin bridge | D94: Repository version history / branch | E94: extraction n/a - NOT delivered - point-in-time extract only | F94: OUT OF SCOPE per SOW: 'version history & audit lineage lost'. Archive PD repository read-only.
